[
  {
    "key": "I",
    "value": "I",
    "firstPerson": true,
    "pluralSubjectForm": "Me",
    "categories": ["proper"],
    "properties": ["size","judgeSize","feeling"]
  },
  {
    "key": "You",
    "value": "You",
    "secondPerson": true,
    "categories": ["proper"],
    "properties": ["size","judgeSize","feeling"]
  },
  {
    "key": "Pig",
    "value": "pig",
    "categories": ["proper"],
    "properties": ["colour","judgeSize","feeling"]
  },
  {
    "key": "Jeffrey",
    "value": "Jeffrey",
    "categories": ["proper","person"],
    "properties": ["size","judgeSize","feeling"]
  },
  {
    "key": "Trish",
    "value": "Trish",
    "categories": ["proper","person"],
    "properties": ["size","judgeSize","feeling"]
  },
  {
    "key": "Banana Tree",
    "value": "Banana Tree",
    "categories": ["common","plant"],
    "properties": ["size","colour"]
  },
  {
    "key": "Banana",
    "value": "Banana",
    "categories": ["common","food"],
    "properties": ["colour","size"]
  },
  {
    "key": "Apple",
    "value": "Apple",
    "categories": ["common","food"],
    "properties": ["colour","size"]
  },
  {
    "key": "Pho",
    "value": "Pho",
    "categories": ["common","food","prepared"],
    "properties": ["size"]
  },
  {
    "key": "Lunch",
    "value": "Lunch",
    "categories": ["abstract","meal","size"],
    "properties": ["size"]
  }
]